ml2p/__init__.py
ml2p/cli.py
ml2p/core.py
ml2p/docker.py
ml2p/errors.py
ml2p/hyperparameters.py
ml2p/cli_commands/__init__.py
ml2p/cli_commands/dataset.py
ml2p/cli_commands/endpoint.py
ml2p/cli_commands/init.py
ml2p/cli_commands/model.py
ml2p/cli_commands/notebook.py
ml2p/cli_commands/repo.py
ml2p/cli_commands/training_job.py
ml2p/cli_commands/utils.py
ml2p-0.6.0.dist-info/licenses/AUTHORS.rst
ml2p-0.6.0.dist-info/licenses/LICENSE
tests/__init__.py
tests/conftest.py
tests/fixtures.py
tests/test_cli.py
tests/test_core.py
tests/test_docker.py
tests/test_errors.py
tests/test_hyperparameters.py
tests/cli_commands/__init__.py
tests/cli_commands/test_dataset.py
tests/cli_commands/test_endpoint.py
tests/cli_commands/test_init.py
tests/cli_commands/test_model.py
tests/cli_commands/test_notebook.py
tests/cli_commands/test_repo.py
tests/cli_commands/test_training_job.py
tests/cli_commands/test_utils.py
tests/fixture_files/__init__.py
ml2p-0.6.0.dist-info/METADATA
ml2p-0.6.0.dist-info/WHEEL
ml2p-0.6.0.dist-info/entry_points.txt
ml2p-0.6.0.dist-info/top_level.txt
ml2p-0.6.0.dist-info/RECORD
