Metadata-Version: 2.4
Name: ml2p
Version: 0.6.0
Summary: A minimum-lovable machine-learning pipeline, built on top of AWS SageMaker.
Home-page: http://github.com/prodigyfinance/ml2p
Author: Prodigy Finance
Author-email: devops@prodigyfinance.com
License: ISCL
Classifier: Development Status :: 4 - Beta
Classifier: License :: OSI Approved :: ISC License (ISCL)
Classifier: Operating System :: POSIX
Classifier: Programming Language :: Python
Classifier: Programming Language :: Python :: 3
Classifier: Programming Language :: Python :: 3.8
Classifier: Programming Language :: Python :: 3.9
License-File: LICENSE
License-File: AUTHORS.rst
Requires-Dist: boto3
Requires-Dist: click
Requires-Dist: Flask
Requires-Dist: werkzeug
Requires-Dist: PyYAML
Provides-Extra: dev
Requires-Dist: black; extra == "dev"
Requires-Dist: bumpversion; extra == "dev"
Requires-Dist: coverage; extra == "dev"
Requires-Dist: flake8; extra == "dev"
Requires-Dist: isort; extra == "dev"
Requires-Dist: pytest; extra == "dev"
Requires-Dist: pytest-cov; extra == "dev"
Requires-Dist: radon[flake8]; extra == "dev"
Requires-Dist: tox; extra == "dev"
Requires-Dist: moto; extra == "dev"
Dynamic: author
Dynamic: author-email
Dynamic: classifier
Dynamic: description
Dynamic: home-page
Dynamic: license
Dynamic: license-file
Dynamic: provides-extra
Dynamic: requires-dist
Dynamic: summary
